universalize/__init__.py
universalize/colors.py
universalize/errors.py
universalize/get_languages.py
universalize/locale.py
universalize/py_universalize.py
universalize/set_primary_language.py
universalize/setup.py
universalize/shared.py
py_universalize-1.0.0.dist-info/LICENSE
py_universalize-1.0.0.dist-info/METADATA
py_universalize-1.0.0.dist-info/WHEEL
py_universalize-1.0.0.dist-info/top_level.txt
py_universalize-1.0.0.dist-info/RECORD
