Metadata-Version: 2.1
Name: py-universalize
Version: 1.0.0
Summary: The internationalization (i18n) library for Python.
Home-page: https://github.com/shriyashwarghade/py_universalize
Author: Shriyash Warghade
Author-email: warghade.shriyash@gmail.com
License: MIT
Project-URL: Bug Reports, https://github.com/shriyashwarghade/py_universalize/issues
Project-URL: Source, https://github.com/shriyashwarghade/py_universalize/
Platform: UNKNOWN
Classifier: License :: OSI Approved :: MIT License
Classifier: Programming Language :: Python :: 3
Classifier: Programming Language :: Python :: 3.7
Classifier: Programming Language :: Python :: 3.8
Classifier: Programming Language :: Python :: 3.9
Classifier: Programming Language :: Python :: 3.10
Classifier: Programming Language :: Python :: 3 :: Only
License-File: LICENSE
